sphinxcontrib_documentedlist-0.6-nspkg.pth
sphinxcontrib/documentedlist.py
sphinxcontrib_documentedlist-0.6.dist-info/DESCRIPTION.rst
sphinxcontrib_documentedlist-0.6.dist-info/METADATA
sphinxcontrib_documentedlist-0.6.dist-info/RECORD
sphinxcontrib_documentedlist-0.6.dist-info/WHEEL
sphinxcontrib_documentedlist-0.6.dist-info/metadata.json
sphinxcontrib_documentedlist-0.6.dist-info/namespace_packages.txt
sphinxcontrib_documentedlist-0.6.dist-info/top_level.txt
