Metadata-Version: 2.0
Name: sphinxcontrib-documentedlist
Version: 0.6
Summary: Sphinx DocumentedList extension
Home-page: https://github.com/chintal/sphinxcontrib-documentedlist
Author: Chintalagiri Shashank
Author-email: shashank@chintal.in
License: BSD
Download-URL: http://pypi.python.org/pypi/sphinxcontrib-documentedlist
Platform: any
Classifier: Development Status :: 5 - Production/Stable
Classifier: Environment :: Console
Classifier: Environment :: Web Environment
Classifier: Intended Audience :: Developers
Classifier: License :: OSI Approved :: BSD License
Classifier: Operating System :: OS Independent
Classifier: Programming Language :: Python
Classifier: Framework :: Sphinx :: Extension
Classifier: Topic :: Documentation
Classifier: Topic :: Utilities
Requires-Dist: Sphinx (>=0.6)
Requires-Dist: six
